bw_superstructure/__about__.py
bw_superstructure/__init__.py
bw_superstructure/calculationsetup.py
bw_superstructure/export.py
bw_superstructure/lcacalculation.py
bw_superstructure/tools.py
bw_superstructure/bwutils/__init__.py
bw_superstructure/bwutils/calculations.py
bw_superstructure/bwutils/commontasks.py
bw_superstructure/bwutils/metadata.py
bw_superstructure/bwutils/multilca.py
bw_superstructure/bwutils/strategies.py
bw_superstructure/bwutils/utils.py
bw_superstructure/superstructure/__init__.py
bw_superstructure/superstructure/activities.py
bw_superstructure/superstructure/dataframe.py
bw_superstructure/superstructure/excel.py
bw_superstructure/superstructure/importer.py
bw_superstructure/superstructure/manager.py
bw_superstructure/superstructure/mlca.py
bw_superstructure/superstructure/utils.py
bw_superstructure-1.0.2.dist-info/METADATA
bw_superstructure-1.0.2.dist-info/WHEEL
bw_superstructure-1.0.2.dist-info/licenses/LICENSE.txt
bw_superstructure-1.0.2.dist-info/RECORD
