Metadata-Version: 2.4
Name: bw-superstructure
Version: 1.0.2
Summary: allows prospective LCA calculations for scenarios using the superstructure and scenario-difference-file approach of the activity-browser and brightway2
Project-URL: Documentation, https://github.com/dlr-ve-esy/bw_superstructure/blob/main/README.md
Project-URL: Issues, https://github.com/dlr-ve-esy/bw_superstructure/issues
Project-URL: Source, https://github.com/dlr-ve-esy/bw_superstructure
Author-email: Carina Harpprecht <Carina.Harpprecht@dlr.de>, Benjamin Fuchs <Benjamin.Fuchs@dlr.de>
License-File: LICENSE.txt
Classifier: Development Status :: 4 - Beta
Classifier: Programming Language :: Python
Classifier: Programming Language :: Python :: 3.7
Classifier: Programming Language :: Python :: 3.8
Classifier: Programming Language :: Python :: 3.9
Classifier: Programming Language :: Python :: 3.10
Classifier: Programming Language :: Python :: Implementation :: CPython
Classifier: Programming Language :: Python :: Implementation :: PyPy
Requires-Python: >=3.7
Requires-Dist: brightway2==2.4
Requires-Dist: bw-migrations==0.1
Requires-Dist: bw2analyzer==0.10
Requires-Dist: bw2calc==1.8.1
Requires-Dist: bw2data==3.6.5
Requires-Dist: bw2io==0.8.6
Requires-Dist: bw2parameters==0.7
Requires-Dist: hatch>=1.14
Requires-Dist: numpy
Requires-Dist: ruamel-yaml
